{
    "Ar36": {
        "error": 0.00015843614516830443, 
        "fit": "previous", 
        "references": [
            {
                "exclude": false, 
                "record_id": "bu-FD-F-570"
            }
        ], 
        "value": 0.0013851818315470405
    }, 
    "Ar37": {
        "error": 0.01167592786400345, 
        "fit": "previous", 
        "references": [
            {
                "exclude": false, 
                "record_id": "bu-FD-F-570"
            }
        ], 
        "value": -0.00023545549210279848
    }, 
    "Ar38": {
        "error": 0.012689810695345501, 
        "fit": "previous", 
        "references": [
            {
                "exclude": false, 
                "record_id": "bu-FD-F-570"
            }
        ], 
        "value": 0.00020633186513274726
    }, 
    "Ar39": {
        "error": 0.02443353438507178, 
        "fit": "previous", 
        "references": [
            {
                "exclude": false, 
                "record_id": "bu-FD-F-570"
            }
        ], 
        "value": 0.023536261602030432
    }, 
    "Ar40": {
        "error": 0.01845389432026808, 
        "fit": "previous", 
        "references": [
            {
                "exclude": false, 
                "record_id": "bu-FD-F-570"
            }
        ], 
        "value": 0.48895300939767544
    }
}