{
    "Ar36": {
        "error": 0.0015089360214691502, 
        "filter_outliers_dict": {
            "filter_outliers": true, 
            "iterations": 1, 
            "std_devs": 10
        }, 
        "fit": "Parabolic", 
        "fn": 375, 
        "include_baseline_error": false, 
        "n": 400, 
        "value": 0.3773577421473916
    }, 
    "Ar37": {
        "error": 0.012019740698391885, 
        "filter_outliers_dict": {
            "filter_outliers": true, 
            "iterations": 1, 
            "std_devs": 2
        }, 
        "fit": "Linear", 
        "fn": 382, 
        "include_baseline_error": false, 
        "n": 400, 
        "value": -0.5356953568480993
    }, 
    "Ar38": {
        "error": 0.012899851779800619, 
        "filter_outliers_dict": {
            "filter_outliers": true, 
            "iterations": 1, 
            "std_devs": 2
        }, 
        "fit": "Linear", 
        "fn": 379, 
        "include_baseline_error": false, 
        "n": 400, 
        "value": 0.002037417235480018
    }, 
    "Ar39": {
        "error": 0.025376351251076738, 
        "filter_outliers_dict": {
            "filter_outliers": true, 
            "iterations": 1, 
            "std_devs": 2
        }, 
        "fit": "Parabolic", 
        "fn": 385, 
        "include_baseline_error": false, 
        "n": 400, 
        "value": 0.4844339174861061
    }, 
    "Ar40": {
        "error": 0.02539634984515243, 
        "filter_outliers_dict": {
            "filter_outliers": true, 
            "iterations": 1, 
            "std_devs": 2
        }, 
        "fit": "Parabolic", 
        "fn": 383, 
        "include_baseline_error": false, 
        "n": 400, 
        "value": 117.16510535896865
    }, 
    "reviewed": true
}