{
    "Ar36": {
        "error": 0.00018727969648893157, 
        "filter_outliers_dict": {
            "filter_outliers": true, 
            "iterations": 2, 
            "std_devs": 2
        }, 
        "fit": "Parabolic", 
        "fn": 364, 
        "include_baseline_error": false, 
        "n": 400, 
        "value": 0.0032727338295676805
    }, 
    "Ar37": {
        "error": 0.011806308972984956, 
        "filter_outliers_dict": {
            "filter_outliers": true, 
            "iterations": 2, 
            "std_devs": 2
        }, 
        "fit": "Linear", 
        "fn": 372, 
        "include_baseline_error": false, 
        "n": 400, 
        "value": -0.5500428133032598
    }, 
    "Ar38": {
        "error": 0.01227107638103526, 
        "filter_outliers_dict": {
            "filter_outliers": true, 
            "iterations": 2, 
            "std_devs": 2
        }, 
        "fit": "Linear", 
        "fn": 369, 
        "include_baseline_error": false, 
        "n": 400, 
        "value": 0.004013766921380457
    }, 
    "Ar39": {
        "error": 0.023664357598561028, 
        "filter_outliers_dict": {
            "filter_outliers": true, 
            "iterations": 2, 
            "std_devs": 2
        }, 
        "fit": "Parabolic", 
        "fn": 377, 
        "include_baseline_error": false, 
        "n": 400, 
        "value": 7.76845356429719
    }, 
    "Ar40": {
        "error": 0.02260726094520858, 
        "filter_outliers_dict": {
            "filter_outliers": true, 
            "iterations": 2, 
            "std_devs": 2
        }, 
        "fit": "Parabolic", 
        "fn": 371, 
        "include_baseline_error": false, 
        "n": 400, 
        "value": 30.384382402778407
    }, 
    "reviewed": true
}