{
    "Ar36": {
        "error": 0.0005359157623301747, 
        "filter_outliers_dict": {
            "filter_outliers": true, 
            "iterations": 2, 
            "std_devs": 2
        }, 
        "fit": "Parabolic", 
        "value": 0.057735649081227414
    }, 
    "Ar37": {
        "error": 0.011487661404589912, 
        "filter_outliers_dict": {
            "filter_outliers": true, 
            "iterations": 2, 
            "std_devs": 2
        }, 
        "fit": "linear", 
        "value": -0.4867311257887381
    }, 
    "Ar38": {
        "error": 0.013455534657099954, 
        "filter_outliers_dict": {
            "filter_outliers": true, 
            "iterations": 2, 
            "std_devs": 2
        }, 
        "fit": "linear", 
        "value": 0.6251153579993121
    }, 
    "Ar39": {
        "error": 0.02425949815365448, 
        "filter_outliers_dict": {
            "filter_outliers": true, 
            "iterations": 2, 
            "std_devs": 2
        }, 
        "fit": "Parabolic", 
        "value": 50.65649476044268
    }, 
    "Ar40": {
        "error": 0.032166224888595746, 
        "filter_outliers_dict": {
            "filter_outliers": true, 
            "iterations": 2, 
            "std_devs": 2
        }, 
        "fit": "Parabolic", 
        "value": 211.54969117972252
    }
}