{
    "Ar36": {
        "error": 0.0007575572834388379, 
        "filter_outliers_dict": {
            "filter_outliers": true, 
            "iterations": 2, 
            "std_devs": 2
        }, 
        "fit": "Parabolic", 
        "value": 0.12134457131917317
    }, 
    "Ar37": {
        "error": 0.01186541955702423, 
        "filter_outliers_dict": {
            "filter_outliers": true, 
            "iterations": 2, 
            "std_devs": 2
        }, 
        "fit": "linear", 
        "value": -0.1780208888941951
    }, 
    "Ar38": {
        "error": 0.012816417415897185, 
        "filter_outliers_dict": {
            "filter_outliers": true, 
            "iterations": 2, 
            "std_devs": 2
        }, 
        "fit": "linear", 
        "value": 0.04738202054613637
    }, 
    "Ar39": {
        "error": 0.02293346291812482, 
        "filter_outliers_dict": {
            "filter_outliers": true, 
            "iterations": 2, 
            "std_devs": 2
        }, 
        "fit": "Parabolic", 
        "value": 8.227785244374104
    }, 
    "Ar40": {
        "error": 0.024748435741856898, 
        "filter_outliers_dict": {
            "filter_outliers": true, 
            "iterations": 2, 
            "std_devs": 2
        }, 
        "fit": "Parabolic", 
        "value": 67.43184061398219
    }
}