{
    "Ar36": {
        "error": 0.0001482889452656239, 
        "filter_outliers_dict": {
            "filter_outliers": true, 
            "iterations": 2, 
            "std_devs": 2
        }, 
        "fit": "Parabolic", 
        "fn": 364, 
        "include_baseline_error": false, 
        "n": 400, 
        "value": 0.001330719832687725
    }, 
    "Ar37": {
        "error": 0.011903486354088829, 
        "filter_outliers_dict": {
            "filter_outliers": true, 
            "iterations": 2, 
            "std_devs": 2
        }, 
        "fit": "Linear", 
        "fn": 374, 
        "include_baseline_error": false, 
        "n": 400, 
        "value": -0.5188731740327711
    }, 
    "Ar38": {
        "error": 0.01288773833889512, 
        "filter_outliers_dict": {
            "filter_outliers": true, 
            "iterations": 2, 
            "std_devs": 2
        }, 
        "fit": "Linear", 
        "fn": 370, 
        "include_baseline_error": false, 
        "n": 400, 
        "value": -0.10804085953188772
    }, 
    "Ar39": {
        "error": 0.022632373051033536, 
        "filter_outliers_dict": {
            "filter_outliers": true, 
            "iterations": 2, 
            "std_devs": 2
        }, 
        "fit": "Parabolic", 
        "fn": 371, 
        "include_baseline_error": false, 
        "n": 400, 
        "value": -0.06265508406734774
    }, 
    "Ar40": {
        "error": 0.02006292208473098, 
        "filter_outliers_dict": {
            "filter_outliers": true, 
            "iterations": 2, 
            "std_devs": 2
        }, 
        "fit": "Parabolic", 
        "fn": 372, 
        "include_baseline_error": false, 
        "n": 400, 
        "value": 0.34621729811211144
    }, 
    "reviewed": true
}