{
    "Ar36": {
        "error": 0.0001419709318328255, 
        "filter_outliers_dict": {
            "filter_outliers": true, 
            "iterations": 2, 
            "std_devs": 2
        }, 
        "fit": "Parabolic", 
        "fn": 363, 
        "include_baseline_error": false, 
        "n": 400, 
        "value": 0.0016465210861215617
    }, 
    "Ar37": {
        "error": 0.012017388651987562, 
        "filter_outliers_dict": {
            "filter_outliers": true, 
            "iterations": 2, 
            "std_devs": 2
        }, 
        "fit": "Linear", 
        "fn": 369, 
        "include_baseline_error": false, 
        "n": 400, 
        "value": -0.539351539435543
    }, 
    "Ar38": {
        "error": 0.013187618740426373, 
        "filter_outliers_dict": {
            "filter_outliers": true, 
            "iterations": 2, 
            "std_devs": 2
        }, 
        "fit": "Linear", 
        "fn": 370, 
        "include_baseline_error": false, 
        "n": 400, 
        "value": -0.12285121442313385
    }, 
    "Ar39": {
        "error": 0.023326622233054973, 
        "filter_outliers_dict": {
            "filter_outliers": true, 
            "iterations": 2, 
            "std_devs": 2
        }, 
        "fit": "Parabolic", 
        "fn": 368, 
        "include_baseline_error": false, 
        "n": 400, 
        "value": -0.03602512584449842
    }, 
    "Ar40": {
        "error": 0.01832939356526878, 
        "filter_outliers_dict": {
            "filter_outliers": true, 
            "iterations": 2, 
            "std_devs": 2
        }, 
        "fit": "Parabolic", 
        "fn": 368, 
        "include_baseline_error": false, 
        "n": 400, 
        "value": 0.4297638576674405
    }, 
    "reviewed": true
}