{
    "Ar36": {
        "error": 0.0004050244793527611, 
        "filter_outliers_dict": {
            "filter_outliers": true, 
            "iterations": 2, 
            "std_devs": 2
        }, 
        "fit": "Parabolic", 
        "fn": 370, 
        "include_baseline_error": false, 
        "n": 400, 
        "value": 0.034274023371844035
    }, 
    "Ar37": {
        "error": 0.011233158323928768, 
        "filter_outliers_dict": {
            "filter_outliers": true, 
            "iterations": 2, 
            "std_devs": 2
        }, 
        "fit": "Linear", 
        "fn": 369, 
        "include_baseline_error": false, 
        "n": 400, 
        "value": -0.12815464786458497
    }, 
    "Ar38": {
        "error": 0.011761542851391802, 
        "filter_outliers_dict": {
            "filter_outliers": true, 
            "iterations": 2, 
            "std_devs": 2
        }, 
        "fit": "Linear", 
        "fn": 359, 
        "include_baseline_error": false, 
        "n": 400, 
        "value": 0.5413103344421676
    }, 
    "Ar39": {
        "error": 0.02578727544198187, 
        "filter_outliers_dict": {
            "filter_outliers": true, 
            "iterations": 2, 
            "std_devs": 2
        }, 
        "fit": "Parabolic", 
        "fn": 368, 
        "include_baseline_error": false, 
        "n": 400, 
        "value": 44.1173288329
    }, 
    "Ar40": {
        "error": 0.030198695035367557, 
        "filter_outliers_dict": {
            "filter_outliers": true, 
            "iterations": 2, 
            "std_devs": 2
        }, 
        "fit": "Parabolic", 
        "fn": 370, 
        "include_baseline_error": false, 
        "n": 400, 
        "value": 177.9976973604784
    }, 
    "reviewed": true
}