{
    "age": 25.708296714857326, 
    "age_err": 0.03583056476460353, 
    "age_kind": "Plateau", 
    "analyses": [
        {
            "plateau_step": true, 
            "tag": "ok", 
            "uuid": "7fda7c2c-85e9-4319-bcd9-781c9c56c311"
        }, 
        {
            "plateau_step": true, 
            "tag": "ok", 
            "uuid": "95a1c545-d621-48b7-b484-a7ce3fe3c9f9"
        }, 
        {
            "plateau_step": true, 
            "tag": "ok", 
            "uuid": "a0c89bd5-6d36-4943-bb14-2bb53dc68913"
        }
    ], 
    "display_age_units": "Ma", 
    "identifier": "65496", 
    "include_j_error_in_individual_analyses": false, 
    "include_j_error_in_mean": true, 
    "include_j_error_in_plateau": true, 
    "irradiation": "NM-289", 
    "kca": 1.3366043988749532, 
    "kca_err": 1.0487891592112506, 
    "kca_kind": "Weighted Mean", 
    "material": "Biotite", 
    "mswd": 1.0871976449117748, 
    "name": "-13p", 
    "nanalyses": 3, 
    "sample": "CC-13A", 
    "uuid": "c6129e11-3edd-45db-88e7-155b1f4576b6"
}