{
    "AX": {
        "error": 0.011756037632238554, 
        "filter_outliers_dict": {
            "filter_outliers": true, 
            "iterations": 2, 
            "std_devs": 2
        }, 
        "fit": "Average", 
        "fn": 111, 
        "include_baseline_error": false, 
        "n": 120, 
        "value": -0.09832994272221333
    }, 
    "H1": {
        "error": 0.011369663192012599, 
        "filter_outliers_dict": {
            "filter_outliers": true, 
            "iterations": 2, 
            "std_devs": 2
        }, 
        "fit": "Average", 
        "fn": 112, 
        "include_baseline_error": false, 
        "n": 120, 
        "value": -0.038439460593508556
    }, 
    "H2": {
        "error": 0.009181853191036104, 
        "filter_outliers_dict": {
            "filter_outliers": true, 
            "iterations": 2, 
            "std_devs": 2
        }, 
        "fit": "Average", 
        "fn": 112, 
        "include_baseline_error": false, 
        "n": 120, 
        "value": -0.06967929327843844
    }, 
    "L1": {
        "error": 0.009713766243362608, 
        "filter_outliers_dict": {
            "filter_outliers": true, 
            "iterations": 2, 
            "std_devs": 2
        }, 
        "fit": "Average", 
        "fn": 111, 
        "include_baseline_error": false, 
        "n": 120, 
        "value": -0.1666620036824145
    }, 
    "L2(CDD)": {
        "error": 0.0, 
        "filter_outliers_dict": {
            "filter_outliers": true, 
            "iterations": 2, 
            "std_devs": 10
        }, 
        "fit": "Average", 
        "fn": 120, 
        "include_baseline_error": false, 
        "n": 120, 
        "value": 0.0
    }
}