{
    "AX": {
        "error": 0.012018776164734051, 
        "filter_outliers_dict": {
            "filter_outliers": true, 
            "iterations": 2, 
            "std_devs": 2
        }, 
        "fit": "Average", 
        "fn": 116, 
        "include_baseline_error": false, 
        "n": 120, 
        "value": -0.11122167727042889
    }, 
    "H1": {
        "error": 0.0097091129594006, 
        "filter_outliers_dict": {
            "filter_outliers": true, 
            "iterations": 2, 
            "std_devs": 2
        }, 
        "fit": "Average", 
        "fn": 112, 
        "include_baseline_error": false, 
        "n": 120, 
        "value": -0.06066341315246453
    }, 
    "H2": {
        "error": 0.0095710802888856, 
        "filter_outliers_dict": {
            "filter_outliers": true, 
            "iterations": 2, 
            "std_devs": 2
        }, 
        "fit": "Average", 
        "fn": 112, 
        "include_baseline_error": false, 
        "n": 120, 
        "value": -0.08223983069599074
    }, 
    "L1": {
        "error": 0.009296771151031027, 
        "filter_outliers_dict": {
            "filter_outliers": true, 
            "iterations": 2, 
            "std_devs": 2
        }, 
        "fit": "Average", 
        "fn": 111, 
        "include_baseline_error": false, 
        "n": 120, 
        "value": -0.17852890279630687
    }, 
    "L2(CDD)": {
        "error": 3.141588656694049e-06, 
        "filter_outliers_dict": {
            "filter_outliers": true, 
            "iterations": 2, 
            "std_devs": 10
        }, 
        "fit": "Average", 
        "fn": 120, 
        "include_baseline_error": false, 
        "n": 120, 
        "value": 7.862234633648768e-06
    }
}